cert/__init__.py
cert/client.py
cert/types.py
cert/bias/__init__.py
cert/bias/models.py
cert/bias/templates.py
cert/integrations/__init__.py
cert/integrations/autogen.py
cert/integrations/crewai.py
cert/integrations/langchain.py
cert_sdk-1.0.3.dist-info/METADATA
cert_sdk-1.0.3.dist-info/WHEEL
cert_sdk-1.0.3.dist-info/licenses/LICENSE
cert_sdk-1.0.3.dist-info/RECORD
