Metadata-Version: 2.4
Name: cert-sdk
Version: 1.0.3
Summary: Python SDK for CERT LLM monitoring dashboard
Project-URL: Homepage, https://dashboard.cert-framework.com
Project-URL: Documentation, https://github.com/Javihaus/cert-sdk#readme
Project-URL: Repository, https://github.com/Javihaus/cert-sdk
Project-URL: Issues, https://github.com/Javihaus/cert-sdk/issues
Author-email: Javier Marin <javier@jmarin.info>
License: Apache-2.0
License-File: LICENSE
Keywords: ai,llm,monitoring,observability,tracing
Classifier: Development Status :: 3 - Alpha
Classifier: Intended Audience :: Developers
Classifier: License :: OSI Approved :: Apache Software License
Classifier: Programming Language :: Python :: 3
Classifier: Programming Language :: Python :: 3.8
Classifier: Programming Language :: Python :: 3.9
Classifier: Programming Language :: Python :: 3.10
Classifier: Programming Language :: Python :: 3.11
Classifier: Programming Language :: Python :: 3.12
Requires-Python: >=3.8
Requires-Dist: requests>=2.25.0
Provides-Extra: all
Requires-Dist: crewai>=0.1.0; extra == 'all'
Requires-Dist: langchain-core>=0.1.0; extra == 'all'
Requires-Dist: langchain>=0.1.0; extra == 'all'
Requires-Dist: pyautogen>=0.2.0; extra == 'all'
Provides-Extra: autogen
Requires-Dist: pyautogen>=0.2.0; extra == 'autogen'
Provides-Extra: crewai
Requires-Dist: crewai>=0.1.0; extra == 'crewai'
Provides-Extra: dev
Requires-Dist: black>=23.0.0; extra == 'dev'
Requires-Dist: mypy>=1.0.0; extra == 'dev'
Requires-Dist: pytest-cov>=4.0.0; extra == 'dev'
Requires-Dist: pytest>=7.0.0; extra == 'dev'
Requires-Dist: ruff>=0.1.0; extra == 'dev'
Provides-Extra: langchain
Requires-Dist: langchain-core>=0.1.0; extra == 'langchain'
Requires-Dist: langchain>=0.1.0; extra == 'langchain'
